pytorchcheckpoint/__init__.py
pytorchcheckpoint/checkpoint.py
pytorchcheckpoint-0.0.5.dist-info/LICENSE
pytorchcheckpoint-0.0.5.dist-info/METADATA
pytorchcheckpoint-0.0.5.dist-info/WHEEL
pytorchcheckpoint-0.0.5.dist-info/top_level.txt
pytorchcheckpoint-0.0.5.dist-info/RECORD
