Metadata-Version: 2.1
Name: pytorchcheckpoint
Version: 0.0.5
Summary: Support PyTorch checkpoints
Home-page: https://github.com/bomri/pytorch-checkpoint.git
Author: Omri Bar
Author-email: baromri@gmail.com
License: UNKNOWN
Platform: UNKNOWN
Classifier: Programming Language :: Python :: 3
Classifier: License :: OSI Approved :: MIT License
Classifier: Operating System :: OS Independent
